vpypi/__init__.py
vpypi/__main__.py
vpypi/_cli.py
vpypi/_core.py
vpypi-0.0.1.dist-info/LICENSE
vpypi-0.0.1.dist-info/WHEEL
vpypi-0.0.1.dist-info/METADATA
vpypi-0.0.1.dist-info/RECORD
