Metadata-Version: 2.1
Name: vpypi
Version: 0.0.1
Summary: vpypi is a CLI tool to verify GPG signature for Python packages on PyPI.
Home-page: https://github.com/orsinium-labs/vpypi
License: MIT
Keywords: pypi,gpg,gnupg
Author: Gram
Author-email: gram@orsinium.dev
Requires-Python: >=3.6
Classifier: Development Status :: 5 - Production/Stable
Classifier: Intended Audience :: Developers
Classifier: License :: OSI Approved :: MIT License
Classifier: Programming Language :: Python
Classifier: Topic :: Software Development
Requires-Dist: requests
Requires-Dist: python-gnupg
Requires-Dist: isort ; extra == "test"
Requires-Dist: mypy ; extra == "test"
Requires-Dist: pytest ; extra == "test"
Provides-Extra: test
